gicopy/__init__.py
gicopy/example.py
gicopy-0.0.1.dist-info/LICENSE
gicopy-0.0.1.dist-info/METADATA
gicopy-0.0.1.dist-info/WHEEL
gicopy-0.0.1.dist-info/top_level.txt
gicopy-0.0.1.dist-info/RECORD
