Metadata-Version: 2.1
Name: gicopy
Version: 0.0.1
Summary: A Python package for the Geodesic ICOsahedral Pixelation (GICOPix).
Home-page: https://github.com/Hao-Wang-Henry/gicopy
Author: Hao Wang
Author-email: wanghao1403@gmail.com
License: UNKNOWN
Project-URL: Bug Tracker, https://github.com/Hao-Wang-Henry/gicopy/issues
Platform: UNKNOWN
Classifier: Programming Language :: Python :: 3
Classifier: License :: OSI Approved :: MIT License
Classifier: Operating System :: OS Independent
Requires-Python: >=3.6
License-File: LICENSE
